[{"rank": 1, "title": "Killing Me Softly With His Song", "artist": "Roberta Flack", "peakPos": 1, "lastPos": 1, "weeks": 6, "isNew": false, "image": null}, {"rank": 2, "title": "Dueling Banjos", "artist": "Deliverance/Eric Weissberg & Steve Mandell", "peakPos": 2, "lastPos": 2, "weeks": 8, "isNew": false, "image": null}, {"rank": 3, "title": "Last Song", "artist": "Edward Bear", "peakPos": 3, "lastPos": 7, "weeks": 12, "isNew": false, "image": null}, {"rank": 4, "title": "Could It Be I'm Falling In Love", "artist": "The Spinners", "peakPos": 4, "lastPos": 5, "weeks": 10, "isNew": false, "image": null}, {"rank": 5, "title": "Crocodile Rock", "artist": "Elton John", "peakPos": 1, "lastPos": 3, "weeks": 13, "isNew": false, "image": "https://charts-static.billboard.com/img/1970/08/elton-john-0rc-180x180.jpg"}, {"rank": 6, "title": "You're So Vain", "artist": "Carly Simon", "peakPos": 1, "lastPos": 4, "weeks": 14, "isNew": false, "image": "https://charts-static.billboard.com/img/1972/12/carly-simon-ad8-youresovain-qtx-180x180.jpg"}, {"rank": 7, "title": "Love Train", "artist": "The O'Jays", "peakPos": 7, "lastPos": 9, "weeks": 7, "isNew": false, "image": "https://www.billboard.com/wp-content/themes/vip/pmc-billboard-2021/assets/public/lazyload-fallback.gif"}, {"rank": 8, "title": "Also Sprach Zarathustra (2001)", "artist": "Deodato", "peakPos": 8, "lastPos": 18, "weeks": 5, "isNew": false, "image": "https://charts-static.billboard.com/img/1973/01/deodato-zxs-180x180.jpg"}, {"rank": 9, "title": "Rocky Mountain High", "artist": "John Denver", "peakPos": 9, "lastPos": 10, "weeks": 15, "isNew": false, "image": "https://charts-static.billboard.com/img/1969/10/john-denver-n9q-180x180.jpg"}, {"rank": 10, "title": "Don't Expect Me To Be Your Friend", "artist": "Lobo", "peakPos": 8, "lastPos": 8, "weeks": 10, "isNew": false, "image": "https://www.billboard.com/wp-content/themes/vip/pmc-billboard-2021/assets/public/lazyload-fallback.gif"}, {"rank": 11, "title": "The Cover Of \"Rolling Stone\"", "artist": "Dr. Hook And The Medicine Show", "peakPos": 11, "lastPos": 15, "weeks": 14, "isNew": false, "image": "https://charts-static.billboard.com/img/1972/04/dr-hook-5qn-180x180.jpg"}, {"rank": 12, "title": "Daddy's Home", "artist": "Jermaine Jackson", "peakPos": 12, "lastPos": 12, "weeks": 13, "isNew": false, "image": "https://charts-static.billboard.com/img/1972/08/jermaine-jackson-cx6-180x180.jpg"}, {"rank": 13, "title": "Dancing In The Moonlight", "artist": "King Harvest", "peakPos": 13, "lastPos": 13, "weeks": 19, "isNew": false, "image": "https://charts-static.billboard.com/img/1972/10/king-harvest-000-dancinginthemoonlight-dj1-180x180.jpg"}, {"rank": 14, "title": "Do It Again", "artist": "Steely Dan", "peakPos": 6, "lastPos": 6, "weeks": 16, "isNew": false, "image": "https://www.billboard.com/wp-content/themes/vip/pmc-billboard-2021/assets/public/lazyload-fallback.gif"}, {"rank": 15, "title": "Oh, Babe, What Would You Say?", "artist": "Hurricane Smith", "peakPos": 3, "lastPos": 11, "weeks": 14, "isNew": false, "image": "https://www.billboard.com/wp-content/themes/vip/pmc-billboard-2021/assets/public/lazyload-fallback.gif"}, {"rank": 16, "title": "Jambalaya (On The Bayou)", "artist": "The Blue Ridge Rangers", "peakPos": 16, "lastPos": 16, "weeks": 14, "isNew": false, "image": "https://charts-static.billboard.com/img/1972/12/john-fogerty-q66-180x180.jpg"}, {"rank": 17, "title": "I'm Just A Singer (In A Rock And Roll Band)", "artist": "The Moody Blues", "peakPos": 17, "lastPos": 22, "weeks": 5, "isNew": false, "image": "https://www.billboard.com/wp-content/themes/vip/pmc-billboard-2021/assets/public/lazyload-fallback.gif"}, {"rank": 18, "title": "Do You Want To Dance?", "artist": "Bette Midler", "peakPos": 18, "lastPos": 19, "weeks": 11, "isNew": false, "image": "https://www.billboard.com/wp-content/themes/vip/pmc-billboard-2021/assets/public/lazyload-fallback.gif"}, {"rank": 19, "title": "Danny's Song", "artist": "Anne Murray", "peakPos": 19, "lastPos": 26, "weeks": 9, "isNew": false, "image": "https://www.billboard.com/wp-content/themes/vip/pmc-billboard-2021/assets/public/lazyload-fallback.gif"}, {"rank": 20, "title": "Neither One Of Us (Wants To Be The First To Say Goodbye)", "artist": "Gladys Knight And The Pips", "peakPos": 20, "lastPos": 31, "weeks": 6, "isNew": false, "image": "https://www.billboard.com/wp-content/themes/vip/pmc-billboard-2021/assets/public/lazyload-fallback.gif"}, {"rank": 21, "title": "Dreidel", "artist": "Don McLean", "peakPos": 21, "lastPos": 21, "weeks": 11, "isNew": false, "image": "https://www.billboard.com/wp-content/themes/vip/pmc-billboard-2021/assets/public/lazyload-fallback.gif"}, {"rank": 22, "title": "Break Up To Make Up", "artist": "The Stylistics", "peakPos": 22, "lastPos": 42, "weeks": 4, "isNew": false, "image": "https://www.billboard.com/wp-content/themes/vip/pmc-billboard-2021/assets/public/lazyload-fallback.gif"}, {"rank": 23, "title": "Peaceful Easy Feeling", "artist": "Eagles", "peakPos": 23, "lastPos": 24, "weeks": 10, "isNew": false, "image": "https://charts-static.billboard.com/img/1972/06/eagles-3gb-180x180.jpg"}, {"rank": 24, "title": "Aubrey", "artist": "Bread", "peakPos": 24, "lastPos": 27, "weeks": 5, "isNew": false, "image": "https://www.billboard.com/wp-content/themes/vip/pmc-billboard-2021/assets/public/lazyload-fallback.gif"}, {"rank": 25, "title": "Why Can't We Live Together", "artist": "Timmy Thomas", "peakPos": 3, "lastPos": 14, "weeks": 15, "isNew": false, "image": "https://www.billboard.com/wp-content/themes/vip/pmc-billboard-2021/assets/public/lazyload-fallback.gif"}, {"rank": 26, "title": "Big City Miss Ruth Ann", "artist": "Gallery", "peakPos": 26, "lastPos": 29, "weeks": 10, "isNew": false, "image": "https://www.billboard.com/wp-content/themes/vip/pmc-billboard-2021/assets/public/lazyload-fallback.gif"}, {"rank": 27, "title": "I Got Ants In My Pants (and i want to dance) (Part 1)", "artist": "James Brown", "peakPos": 27, "lastPos": 28, "weeks": 7, "isNew": false, "image": "https://www.billboard.com/wp-content/themes/vip/pmc-billboard-2021/assets/public/lazyload-fallback.gif"}, {"rank": 28, "title": "Call Me (Come Back Home)", "artist": "Al Green", "peakPos": 28, "lastPos": 48, "weeks": 3, "isNew": false, "image": "https://www.billboard.com/wp-content/themes/vip/pmc-billboard-2021/assets/public/lazyload-fallback.gif"}, {"rank": 29, "title": "Superstition", "artist": "Stevie Wonder", "peakPos": 1, "lastPos": 17, "weeks": 16, "isNew": false, "image": "https://www.billboard.com/wp-content/themes/vip/pmc-billboard-2021/assets/public/lazyload-fallback.gif"}, {"rank": 30, "title": "Hummingbird", "artist": "Seals & Crofts", "peakPos": 30, "lastPos": 33, "weeks": 7, "isNew": false, "image": "https://www.billboard.com/wp-content/themes/vip/pmc-billboard-2021/assets/public/lazyload-fallback.gif"}, {"rank": 31, "title": "Space Oddity", "artist": "David Bowie", "peakPos": 31, "lastPos": 36, "weeks": 6, "isNew": false, "image": "https://www.billboard.com/wp-content/themes/vip/pmc-billboard-2021/assets/public/lazyload-fallback.gif"}, {"rank": 32, "title": "Give Me Your Love", "artist": "Barbara Mason", "peakPos": 32, "lastPos": 34, "weeks": 8, "isNew": false, "image": "https://www.billboard.com/wp-content/themes/vip/pmc-billboard-2021/assets/public/lazyload-fallback.gif"}, {"rank": 33, "title": "Ain't No Woman (Like The One I've Got)", "artist": "Four Tops", "peakPos": 33, "lastPos": 39, "weeks": 5, "isNew": false, "image": "https://www.billboard.com/wp-content/themes/vip/pmc-billboard-2021/assets/public/lazyload-fallback.gif"}, {"rank": 34, "title": "Dead Skunk", "artist": "Loudon Wainwright III", "peakPos": 34, "lastPos": 40, "weeks": 6, "isNew": false, "image": "https://charts-static.billboard.com/img/1973/01/loudon-wainwright-iii-a7t-180x180.jpg"}, {"rank": 35, "title": "Don't Cross The River", "artist": "America", "peakPos": 35, "lastPos": 37, "weeks": 6, "isNew": false, "image": "https://www.billboard.com/wp-content/themes/vip/pmc-billboard-2021/assets/public/lazyload-fallback.gif"}, {"rank": 36, "title": "Stir It Up", "artist": "Johnny Nash", "peakPos": 36, "lastPos": 44, "weeks": 4, "isNew": false, "image": "https://www.billboard.com/wp-content/themes/vip/pmc-billboard-2021/assets/public/lazyload-fallback.gif"}, {"rank": 37, "title": "Living Together, Growing Together", "artist": "The 5th Dimension", "peakPos": 32, "lastPos": 32, "weeks": 9, "isNew": false, "image": "https://www.billboard.com/wp-content/themes/vip/pmc-billboard-2021/assets/public/lazyload-fallback.gif"}, {"rank": 38, "title": "Kissing My Love", "artist": "Bill Withers", "peakPos": 38, "lastPos": 46, "weeks": 5, "isNew": false, "image": "https://www.billboard.com/wp-content/themes/vip/pmc-billboard-2021/assets/public/lazyload-fallback.gif"}, {"rank": 39, "title": "Good Morning Heartache", "artist": "Diana Ross", "peakPos": 39, "lastPos": 41, "weeks": 8, "isNew": false, "image": "https://www.billboard.com/wp-content/themes/vip/pmc-billboard-2021/assets/public/lazyload-fallback.gif"}, {"rank": 40, "title": "Soul Song", "artist": "Joe Stampley", "peakPos": 40, "lastPos": 43, "weeks": 9, "isNew": false, "image": "https://charts-static.billboard.com/img/1971/02/joe-stampley-3gh-180x180.jpg"}, {"rank": 41, "title": "Master Of Eyes (The Deepness Of Your Eyes)", "artist": "Aretha Franklin", "peakPos": 41, "lastPos": 53, "weeks": 4, "isNew": false, "image": "https://www.billboard.com/wp-content/themes/vip/pmc-billboard-2021/assets/public/lazyload-fallback.gif"}, {"rank": 42, "title": "Hello Hurray", "artist": "Alice Cooper", "peakPos": 42, "lastPos": 50, "weeks": 5, "isNew": false, "image": "https://charts-static.billboard.com/img/1969/06/alice-cooper-916-180x180.jpg"}, {"rank": 43, "title": "The World Is A Ghetto", "artist": "War", "peakPos": 7, "lastPos": 20, "weeks": 16, "isNew": false, "image": "https://www.billboard.com/wp-content/themes/vip/pmc-billboard-2021/assets/public/lazyload-fallback.gif"}, {"rank": 44, "title": "Rosalie", "artist": "Sam Neely", "peakPos": 44, "lastPos": 49, "weeks": 6, "isNew": false, "image": "https://www.billboard.com/wp-content/themes/vip/pmc-billboard-2021/assets/public/lazyload-fallback.gif"}, {"rank": 45, "title": "Peaceful", "artist": "Helen Reddy", "peakPos": 45, "lastPos": 54, "weeks": 5, "isNew": false, "image": "https://www.billboard.com/wp-content/themes/vip/pmc-billboard-2021/assets/public/lazyload-fallback.gif"}, {"rank": 46, "title": "Masterpiece", "artist": "The Temptations", "peakPos": 46, "lastPos": 63, "weeks": 2, "isNew": false, "image": "https://charts-static.billboard.com/img/1960/04/the-temptations-mnb-180x180.jpg"}, {"rank": 47, "title": "Today I Started Loving You Again", "artist": "Bettye Swann", "peakPos": 47, "lastPos": 51, "weeks": 6, "isNew": false, "image": "https://charts-static.billboard.com/img/1965/02/bettye-swann-6cf-180x180.jpg"}, {"rank": 48, "title": "A Letter To Myself", "artist": "The Chi-lites", "peakPos": 48, "lastPos": 55, "weeks": 4, "isNew": false, "image": "https://charts-static.billboard.com/img/1969/02/the-chi-lites-bwb-180x180.jpg"}, {"rank": 49, "title": "Sing", "artist": "Carpenters", "peakPos": 49, "lastPos": 61, "weeks": 2, "isNew": false, "image": "https://www.billboard.com/wp-content/themes/vip/pmc-billboard-2021/assets/public/lazyload-fallback.gif"}, {"rank": 50, "title": "One Less Set Of Footsteps", "artist": "Jim Croce", "peakPos": 50, "lastPos": 57, "weeks": 5, "isNew": false, "image": "https://charts-static.billboard.com/img/1972/07/jim-croce-elh-180x180.jpg"}, {"rank": 51, "title": "Control Of Me", "artist": "Les Emmerson", "peakPos": 51, "lastPos": 56, "weeks": 8, "isNew": false, "image": "https://www.billboard.com/wp-content/themes/vip/pmc-billboard-2021/assets/public/lazyload-fallback.gif"}, {"rank": 52, "title": "Cook With Honey", "artist": "Judy Collins", "peakPos": 52, "lastPos": 64, "weeks": 4, "isNew": false, "image": "https://charts-static.billboard.com/img/1964/03/judy-collins-37b-180x180.jpg"}, {"rank": 53, "title": "Love Jones", "artist": "Brighter Side Of Darkness", "peakPos": 16, "lastPos": 23, "weeks": 13, "isNew": false, "image": "https://www.billboard.com/wp-content/themes/vip/pmc-billboard-2021/assets/public/lazyload-fallback.gif"}, {"rank": 54, "title": "The Message", "artist": "Cymande", "peakPos": 54, "lastPos": 59, "weeks": 7, "isNew": false, "image": "https://charts-static.billboard.com/img/1973/01/cymande-it8-180x180.jpg"}, {"rank": 55, "title": "Keep On Singing", "artist": "Austin Roberts", "peakPos": 55, "lastPos": 60, "weeks": 5, "isNew": false, "image": "https://www.billboard.com/wp-content/themes/vip/pmc-billboard-2021/assets/public/lazyload-fallback.gif"}, {"rank": 56, "title": "Tie A Yellow Ribbon Round The Ole Oak Tree", "artist": "Dawn Featuring Tony Orlando", "peakPos": 56, "lastPos": 68, "weeks": 3, "isNew": false, "image": "https://www.billboard.com/wp-content/themes/vip/pmc-billboard-2021/assets/public/lazyload-fallback.gif"}, {"rank": 57, "title": "Bitter Bad", "artist": "Melanie", "peakPos": 57, "lastPos": 66, "weeks": 3, "isNew": false, "image": "https://charts-static.billboard.com/img/1969/11/melanie-ssw-180x180.jpg"}, {"rank": 58, "title": "Love Is What You Make It", "artist": "The Grass Roots", "peakPos": 58, "lastPos": 62, "weeks": 6, "isNew": false, "image": "https://charts-static.billboard.com/img/1966/06/the-grass-roots-uql-180x180.jpg"}, {"rank": 59, "title": "The Night The Lights Went Out In Georgia", "artist": "Vicki Lawrence", "peakPos": 59, "lastPos": 80, "weeks": 4, "isNew": false, "image": "https://charts-static.billboard.com/img/1973/02/vicki-lawrence-t8w-180x180.jpg"}, {"rank": 60, "title": "Little Willy", "artist": "The Sweet", "peakPos": 60, "lastPos": 74, "weeks": 7, "isNew": false, "image": "https://www.billboard.com/wp-content/themes/vip/pmc-billboard-2021/assets/public/lazyload-fallback.gif"}, {"rank": 61, "title": "Pardon Me Sir", "artist": "Joe Cocker", "peakPos": 61, "lastPos": 72, "weeks": 3, "isNew": false, "image": "https://www.billboard.com/wp-content/themes/vip/pmc-billboard-2021/assets/public/lazyload-fallback.gif"}, {"rank": 62, "title": "Trouble Man", "artist": "Marvin Gaye", "peakPos": 7, "lastPos": 25, "weeks": 12, "isNew": false, "image": "https://www.billboard.com/wp-content/themes/vip/pmc-billboard-2021/assets/public/lazyload-fallback.gif"}, {"rank": 63, "title": "Daisy A Day", "artist": "Jud Strunk", "peakPos": 63, "lastPos": 78, "weeks": 3, "isNew": false, "image": "https://www.billboard.com/wp-content/themes/vip/pmc-billboard-2021/assets/public/lazyload-fallback.gif"}, {"rank": 64, "title": "Follow Your Daughter Home", "artist": "The Guess Who", "peakPos": 64, "lastPos": 69, "weeks": 5, "isNew": false, "image": "https://charts-static.billboard.com/img/1965/05/the-guess-who-oc9-180x180.jpg"}, {"rank": 65, "title": "Superman", "artist": "Donna Fargo", "peakPos": 65, "lastPos": 73, "weeks": 2, "isNew": false, "image": "https://charts-static.billboard.com/img/1972/03/donna-fargo-m4s-180x180.jpg"}, {"rank": 66, "title": "Lost Horizon", "artist": "Shawn Phillips", "peakPos": 66, "lastPos": 70, "weeks": 4, "isNew": false, "image": "https://charts-static.billboard.com/img/1972/12/shawn-phillips-lao-180x180.jpg"}, {"rank": 67, "title": "Magic Woman Touch", "artist": "The Hollies", "peakPos": 67, "lastPos": 77, "weeks": 4, "isNew": false, "image": "https://www.billboard.com/wp-content/themes/vip/pmc-billboard-2021/assets/public/lazyload-fallback.gif"}, {"rank": 68, "title": "How Can I Tell You", "artist": "Travis Wammack", "peakPos": 68, "lastPos": 71, "weeks": 7, "isNew": false, "image": "https://charts-static.billboard.com/img/1964/11/travis-wammack-ote-180x180.jpg"}, {"rank": 69, "title": "Step By Step", "artist": "Joe Simon", "peakPos": 69, "lastPos": 76, "weeks": 3, "isNew": false, "image": "https://charts-static.billboard.com/img/1964/10/joe-simon-blx-180x180.jpg"}, {"rank": 70, "title": "Do It In The Name Of Love", "artist": "Candi Staton", "peakPos": 70, "lastPos": 75, "weeks": 5, "isNew": false, "image": "https://www.billboard.com/wp-content/themes/vip/pmc-billboard-2021/assets/public/lazyload-fallback.gif"}, {"rank": 71, "title": "One Man Band (Plays All Alone)", "artist": "Ronnie Dyson", "peakPos": 71, "lastPos": 81, "weeks": 3, "isNew": false, "image": "https://www.billboard.com/wp-content/themes/vip/pmc-billboard-2021/assets/public/lazyload-fallback.gif"}, {"rank": 72, "title": "Walk On The Wild Side", "artist": "Lou Reed", "peakPos": 72, "lastPos": 84, "weeks": 3, "isNew": false, "image": "https://charts-static.billboard.com/img/1972/06/lou-reed-fsf-180x180.jpg"}, {"rank": 73, "title": "Drift Away", "artist": "Dobie Gray", "peakPos": 73, "lastPos": 85, "weeks": 2, "isNew": false, "image": "https://www.billboard.com/wp-content/themes/vip/pmc-billboard-2021/assets/public/lazyload-fallback.gif"}, {"rank": 74, "title": "Boo, Boo, Don't 'Cha Be Blue", "artist": "Tommy James", "peakPos": 74, "lastPos": 82, "weeks": 3, "isNew": false, "image": "https://www.billboard.com/wp-content/themes/vip/pmc-billboard-2021/assets/public/lazyload-fallback.gif"}, {"rank": 75, "title": "One Man Parade", "artist": "James Taylor", "peakPos": 75, "lastPos": 0, "weeks": 1, "isNew": true, "image": "https://www.billboard.com/wp-content/themes/vip/pmc-billboard-2021/assets/public/lazyload-fallback.gif"}, {"rank": 76, "title": "Palace Guard", "artist": "Rick Nelson And The Stone Canyon Band", "peakPos": 65, "lastPos": 65, "weeks": 5, "isNew": false, "image": "https://www.billboard.com/wp-content/themes/vip/pmc-billboard-2021/assets/public/lazyload-fallback.gif"}, {"rank": 77, "title": "Wildflower", "artist": "Skylark", "peakPos": 77, "lastPos": 86, "weeks": 3, "isNew": false, "image": "https://charts-static.billboard.com/img/1973/02/skylark-86k-180x180.jpg"}, {"rank": 78, "title": "Pinball Wizard/See Me, Feel Me", "artist": "The New Seekers", "peakPos": 78, "lastPos": 87, "weeks": 2, "isNew": false, "image": "https://www.billboard.com/wp-content/themes/vip/pmc-billboard-2021/assets/public/lazyload-fallback.gif"}, {"rank": 79, "title": "The Cisco Kid", "artist": "War", "peakPos": 79, "lastPos": 0, "weeks": 1, "isNew": true, "image": "https://www.billboard.com/wp-content/themes/vip/pmc-billboard-2021/assets/public/lazyload-fallback.gif"}, {"rank": 80, "title": "Dream Me Home", "artist": "Mac Davis", "peakPos": 80, "lastPos": 83, "weeks": 3, "isNew": false, "image": "https://www.billboard.com/wp-content/themes/vip/pmc-billboard-2021/assets/public/lazyload-fallback.gif"}, {"rank": 81, "title": "Out Of The Question", "artist": "Gilbert O'Sullivan", "peakPos": 81, "lastPos": 0, "weeks": 1, "isNew": true, "image": "https://www.billboard.com/wp-content/themes/vip/pmc-billboard-2021/assets/public/lazyload-fallback.gif"}, {"rank": 82, "title": "The Twelfth Of Never", "artist": "Donny Osmond", "peakPos": 82, "lastPos": 0, "weeks": 1, "isNew": true, "image": "https://charts-static.billboard.com/img/1971/03/donny-osmond-fis-180x180.jpg"}, {"rank": 83, "title": "Bell Bottom Blues", "artist": "Eric Clapton", "peakPos": 83, "lastPos": 89, "weeks": 3, "isNew": false, "image": "https://charts-static.billboard.com/img/1970/02/eric-clapton-pmc-180x180.jpg"}, {"rank": 84, "title": "If You Gotta Break Another Heart", "artist": "Albert Hammond", "peakPos": 84, "lastPos": 0, "weeks": 1, "isNew": true, "image": "https://charts-static.billboard.com/img/1972/07/albert-hammond-ciw-180x180.jpg"}, {"rank": 85, "title": "Good Morning", "artist": "Michael Redway", "peakPos": 85, "lastPos": 88, "weeks": 4, "isNew": false, "image": "https://www.billboard.com/wp-content/themes/vip/pmc-billboard-2021/assets/public/lazyload-fallback.gif"}, {"rank": 86, "title": "Stuck In The Middle With You", "artist": "Stealers Wheel", "peakPos": 86, "lastPos": 0, "weeks": 1, "isNew": true, "image": "https://www.billboard.com/wp-content/themes/vip/pmc-billboard-2021/assets/public/lazyload-fallback.gif"}, {"rank": 87, "title": "Sail On Sailor", "artist": "The Beach Boys", "peakPos": 87, "lastPos": 92, "weeks": 2, "isNew": false, "image": "https://charts-static.billboard.com/img/1973/02/the-beach-boys-nds-180x180.jpg"}, {"rank": 88, "title": "Yesterday I Had The Blues", "artist": "Harold Melvin And The Blue Notes", "peakPos": 88, "lastPos": 0, "weeks": 1, "isNew": true, "image": "https://www.billboard.com/wp-content/themes/vip/pmc-billboard-2021/assets/public/lazyload-fallback.gif"}, {"rank": 89, "title": "Wish That I Could Talk To You", "artist": "The Sylvers", "peakPos": 89, "lastPos": 90, "weeks": 5, "isNew": false, "image": "https://charts-static.billboard.com/img/1972/09/the-sylvers-vqe-180x180.jpg"}, {"rank": 90, "title": "Girl You Need A Change Of Mind (Part 1)", "artist": "Eddie Kendricks", "peakPos": 90, "lastPos": 95, "weeks": 2, "isNew": false, "image": "https://charts-static.billboard.com/img/1971/05/eddie-kendricks-bkn-180x180.jpg"}, {"rank": 91, "title": "Names, Tags, Numbers & Labels", "artist": "The Association", "peakPos": 91, "lastPos": 93, "weeks": 2, "isNew": false, "image": "https://www.billboard.com/wp-content/themes/vip/pmc-billboard-2021/assets/public/lazyload-fallback.gif"}, {"rank": 92, "title": "Funky Worm", "artist": "Ohio Players", "peakPos": 92, "lastPos": 94, "weeks": 2, "isNew": false, "image": "https://charts-static.billboard.com/img/1968/02/ohio-players-alh-180x180.jpg"}, {"rank": 93, "title": "Stop, Wait & Listen", "artist": "Circus", "peakPos": 93, "lastPos": 96, "weeks": 2, "isNew": false, "image": "https://www.billboard.com/wp-content/themes/vip/pmc-billboard-2021/assets/public/lazyload-fallback.gif"}, {"rank": 94, "title": "Let Your Yeah Be Yeah", "artist": "Brownsville Station", "peakPos": 94, "lastPos": 0, "weeks": 1, "isNew": true, "image": "https://charts-static.billboard.com/img/1972/10/brownsville-station-n2n-180x180.jpg"}, {"rank": 95, "title": "Teddy Bear Song", "artist": "Barbara Fairchild", "peakPos": 95, "lastPos": 99, "weeks": 2, "isNew": false, "image": "https://www.billboard.com/wp-content/themes/vip/pmc-billboard-2021/assets/public/lazyload-fallback.gif"}, {"rank": 96, "title": "I'm Doin' Fine Now", "artist": "New York City", "peakPos": 96, "lastPos": 0, "weeks": 1, "isNew": true, "image": "https://www.billboard.com/wp-content/themes/vip/pmc-billboard-2021/assets/public/lazyload-fallback.gif"}, {"rank": 97, "title": "Love Music", "artist": "The Raiders", "peakPos": 97, "lastPos": 97, "weeks": 5, "isNew": false, "image": "https://www.billboard.com/wp-content/themes/vip/pmc-billboard-2021/assets/public/lazyload-fallback.gif"}, {"rank": 98, "title": "Hocus Pocus", "artist": "Focus", "peakPos": 98, "lastPos": 0, "weeks": 1, "isNew": true, "image": "https://charts-static.billboard.com/img/1973/01/focus-e35-180x180.jpg"}, {"rank": 99, "title": "River Road", "artist": "Uncle Dog", "peakPos": 99, "lastPos": 0, "weeks": 1, "isNew": true, "image": "https://www.billboard.com/wp-content/themes/vip/pmc-billboard-2021/assets/public/lazyload-fallback.gif"}, {"rank": 100, "title": "We Did It", "artist": "Syl Johnson", "peakPos": 100, "lastPos": 100, "weeks": 2, "isNew": false, "image": "https://www.billboard.com/wp-content/themes/vip/pmc-billboard-2021/assets/public/lazyload-fallback.gif"}]